<?xml version="1.0" encoding="UTF-8"?>

<!--

    Copyright (c) 2017-2019 MuK IT GmbH.

    This file is part of MuK Web Utils 
    (see https://mukit.at).

    This program is free software: you can redistribute it and/or modify
    it under the terms of the GNU Lesser General Public License as published by
    the Free Software Foundation, either version 3 of the License, or
    (at your option) any later version.

    This program is distributed in the hope that it will be useful,
    but WITHOUT ANY WARRANTY; without even the implied warranty of
    MERCHANTABILITY or FITNESS FOR A PARTICULAR PURPOSE.  See the
    GNU Lesser General Public License for more details.

    You should have received a copy of the GNU Lesser General Public License
    along with this program. If not, see <http://www.gnu.org/licenses/>.

  -->

<odoo>

	<record id="res_config_settings_view_form" model="ir.ui.view">
	    <field name="name">res.config.settings.view.form</field>
	    <field name="model">res.config.settings</field>
	    <field name="inherit_id" ref="base_setup.res_config_settings_view_form"/>
	    <field name="arch" type="xml">
	        <div name="storage" position="inside">
	            <div class="col-12 col-lg-6 o_setting_box">
                    <div class="o_setting_left_pane"></div>
                    <div class="o_setting_right_pane">
			            <label for="binary_max_size"/>
			            <div class="text-muted">
			                Maximum allowed file size in MB
			            </div>
			            <div class="mt8">
			                <field name="binary_max_size" class="o_light_label"/>
			            </div>
			        </div>
                </div>
	        </div>
	    </field>
	</record>
	
</odoo>